robocorp/storage/__init__.py
robocorp/storage/_client.py
robocorp/storage/_environment.py
robocorp/storage/_requests.py
robocorp/storage/_types.py
robocorp/storage/_utils.py
robocorp/storage/py.typed
robocorp_storage-1.0.3.dist-info/METADATA
robocorp_storage-1.0.3.dist-info/WHEEL
robocorp_storage-1.0.3.dist-info/RECORD
